emolog/__init__.py
emolog/cli.py
emolog/core/__init__.py
emolog/core/analyzer.py
emolog/core/data_manager.py
emolog/core/emotion_logger.py
emolog/data/body_reactions.json
emolog/data/contexts.json
emolog/data/emotions.json
emolog-0.1.0.dist-info/WHEEL
emolog-0.1.0.dist-info/entry_points.txt
emolog-0.1.0.dist-info/METADATA
emolog-0.1.0.dist-info/RECORD
