Metadata-Version: 2.3
Name: emolog
Version: 0.1.0
Summary: A terminal-based emotion logging tool for developers
Keywords: emotion,logging,mental-health,developer-tools,cli,terminal,self-care,productivity
Author: gmlee
Author-email: gmlee <sld9849@gmail.com>
License: MIT
Classifier: Development Status :: 4 - Beta
Classifier: Environment :: Console
Classifier: Intended Audience :: Developers
Classifier: Intended Audience :: End Users/Desktop
Classifier: License :: OSI Approved :: MIT License
Classifier: Operating System :: OS Independent
Classifier: Programming Language :: Python :: 3
Classifier: Programming Language :: Python :: 3.9
Classifier: Programming Language :: Python :: 3.10
Classifier: Programming Language :: Python :: 3.11
Classifier: Programming Language :: Python :: 3.12
Classifier: Topic :: Software Development :: Libraries :: Python Modules
Classifier: Topic :: System :: Logging
Classifier: Topic :: Terminals
Classifier: Topic :: Utilities
Requires-Dist: click>=8.0.0
Requires-Dist: rich>=13.0.0
Requires-Dist: python-dateutil>=2.8.0
Requires-Dist: build>=0.10.0 ; extra == 'build'
Requires-Dist: twine>=4.0.0 ; extra == 'build'
Requires-Dist: black>=23.0.0 ; extra == 'dev'
Requires-Dist: isort>=5.12.0 ; extra == 'dev'
Maintainer: gmlee
Maintainer-email: gmlee <sld9849@gmail.com>
Requires-Python: >=3.9
Project-URL: Changelog, https://github.com/gmlee/emolog/releases
Project-URL: Documentation, https://github.com/gmlee/emolog#readme
Project-URL: Homepage, https://github.com/gmlee/emolog
Project-URL: Issues, https://github.com/gmlee/emolog/issues
Project-URL: Repository, https://github.com/gmlee/emolog
Provides-Extra: build
Provides-Extra: dev
